controltheorylib/__init__.py
controltheorylib/bode.py
controltheorylib/controlsystem.py
controltheorylib/mech_vis.py
controltheorylib/nyquist.py
controltheorylib/pzmap.py
controltheorylib-1.0.0.dist-info/licenses/LICENSE
controltheorylib-1.0.0.dist-info/METADATA
controltheorylib-1.0.0.dist-info/WHEEL
controltheorylib-1.0.0.dist-info/top_level.txt
controltheorylib-1.0.0.dist-info/RECORD
