Metadata-Version: 2.4
Name: controltheorylib
Version: 1.0.0
Summary: Control Theory Library for creating mathematical animations with Manim
Home-page: https://github.com/JortStamme/Controltheorylibrary
Author: Jort Stammen
Author-email: Jort Stammen <j.r.k.stammen@student.tue.nl>
License: MIT
Project-URL: Homepage, https://github.com/yourusername/controltheorylib
Project-URL: Documentation, https://controltheorylibrary.readthedocs.io/en/latest/
Requires-Python: >=3.8
License-File: LICENSE
Requires-Dist: numpy>=1.21.0
Requires-Dist: scipy>=1.7.0
Requires-Dist: sympy>=1.9
Requires-Dist: matplotlib>=3.5.0
Provides-Extra: docs
Requires-Dist: sphinx>=7.0.0; extra == "docs"
Requires-Dist: sphinx-rtd-theme>=1.0.0; extra == "docs"
Requires-Dist: sphinx-autodoc-typehints>=1.0.0; extra == "docs"
Requires-Dist: myst-parser>=0.18.0; extra == "docs"
Requires-Dist: sphinx-design>=0.3.0; extra == "docs"
Requires-Dist: sphinxcontrib-programoutput>=1.0.0; extra == "docs"
Dynamic: author
Dynamic: home-page
Dynamic: license-file
